{
  "msg": "success",
  "filename":"reserveByDay",
  "url":"/reserve",
  "res":{
    "code": 1,
    "msg": "获得按天预定的订单信息",
    "data":{
      "gym": {
        "id": 10,
        "title": "珠海游泳馆",
        "description": "珠海校园游泳池暑期开放时间：6：30-8：00，16：30-18：00，19：30-21：00。 可以网上预订和现场扣预订，网上可提前一天预订。 建议先网上预订，现场验证可节省入场时间。如现场预订需输入校园卡密码，会增加入场时间。",
        "siteNumber": 0,
        "addr": "场地地址： 综合训练馆",
        "rank": 4,
        "open_time": "0:2018-04-23 06:00 ~ 08:00, 1:2018-04-24 16:00 ~ 19:00",
        "time_type": 1,
        "status": "0:0 1:0",
        "price": "11"
        }
    }
  }

}
